cognisim/__init__.py
cognisim/device/android/__init__.py
cognisim/device/android/android_device.py
cognisim/device/android/android_ui.py
cognisim/device/android/android_view_hierarchy.py
cognisim/device/device.py
cognisim/device/device_factory.py
cognisim/device/ios/__init__.py
cognisim/device/ios/ios_device.py
cognisim/device/ios/ios_view_hierarchy.py
cognisim/device/ios_device.py
cognisim/utils/constants.py
cognisim-0.1.0.dist-info/LICENSE
cognisim-0.1.0.dist-info/METADATA
cognisim-0.1.0.dist-info/WHEEL
cognisim-0.1.0.dist-info/RECORD
