Metadata-Version: 2.1
Name: cognisim
Version: 0.1.0
Summary: A package for mobile app adaptation and testing
Home-page: https://mobileadapt.revyl.ai
License: MIT
Author: Revyl AI
Author-email: anam@revyl.ai
Requires-Python: >=3.12,<4.0
Classifier: Development Status :: 3 - Alpha
Classifier: Intended Audience :: Developers
Classifier: License :: OSI Approved :: MIT License
Classifier: Operating System :: OS Independent
Classifier: Programming Language :: Python :: 3
Classifier: Programming Language :: Python :: 3.12
Classifier: Programming Language :: Python :: 3.7
Classifier: Programming Language :: Python :: 3.8
Classifier: Programming Language :: Python :: 3.9
Requires-Dist: appium-python-client
Requires-Dist: attrs
Requires-Dist: loguru
Requires-Dist: lxml
Requires-Dist: numpy
Requires-Dist: openai (>=1.43.0,<2.0.0)
Requires-Dist: opencv-python (>=4.10.0.84,<5.0.0.0)
Requires-Dist: pillow (>=10.4.0,<11.0.0)
Requires-Dist: retrying (>=1.3.4,<2.0.0)
Requires-Dist: setuptools (>=75.2.0,<76.0.0)
Requires-Dist: str2bool (>=1.1,<2.0)
Project-URL: Bug Tracker, https://github.com/RevylAI/Mobileadapt/issues
Project-URL: Repository, https://github.com/RevylAI/Mobileadapt
